sqleyes/__init__.py
sqleyes/cli.py
sqleyes/main.py
sqleyes/definitions/__init__.py
sqleyes/definitions/definitions.py
sqleyes/definitions/antipatterns/__init__.py
sqleyes/definitions/antipatterns/ambiguous_groups.md
sqleyes/definitions/antipatterns/fear_of_the_unknown.md
sqleyes/definitions/antipatterns/implicit_columns.md
sqleyes/definitions/antipatterns/poor_mans_search_engine.md
sqleyes/definitions/antipatterns/random_selection.md
sqleyes/definitions/antipatterns/spaghetti_query.md
sqleyes/detector/__init__.py
sqleyes/detector/detector.py
sqleyes/detector/detector_output.py
sqleyes/detector/antipatterns/__init__.py
sqleyes/detector/antipatterns/abstract_base_class.py
sqleyes/detector/antipatterns/ambiguous_groups.py
sqleyes/detector/antipatterns/fear_of_the_unknown.py
sqleyes/detector/antipatterns/implicit_columns.py
sqleyes/detector/antipatterns/poor_mans_search_engine.py
sqleyes/detector/antipatterns/random_selection.py
sqleyes/detector/antipatterns/spaghetti_query.py
sqleyes/printer/__init__.py
sqleyes/printer/printer.py
sqleyes/utils/__init__.py
sqleyes/utils/code_complexity_metrics.py
sqleyes/utils/load_file.py
sqleyes/utils/query_functions.py
sqleyes/utils/query_keywords.py
sqleyes-0.5.0.dist-info/LICENSE
sqleyes-0.5.0.dist-info/METADATA
sqleyes-0.5.0.dist-info/WHEEL
sqleyes-0.5.0.dist-info/entry_points.txt
sqleyes-0.5.0.dist-info/top_level.txt
sqleyes-0.5.0.dist-info/RECORD
