Metadata-Version: 2.1
Name: sqleyes
Version: 0.5.0
Summary: A CLI in Python that analyzes raw SQL queries for common anti-patterns
Home-page: https://leonardomathon.nl
Author: Leonardo Mathon
Author-email: info@leonardomathon.nl
License: MIT
Keywords: SQL,anti-patterns,analysis
Platform: unix
Platform: linux
Platform: osx
Platform: cygwin
Platform: win32
Classifier: Programming Language :: Python :: 3
Classifier: Programming Language :: Python :: 3 :: Only
Classifier: Programming Language :: Python :: 3.6
Classifier: Programming Language :: Python :: 3.7
Classifier: Programming Language :: Python :: 3.8
Classifier: Programming Language :: Python :: 3.9
Classifier: License :: OSI Approved :: MIT License
Classifier: Operating System :: OS Independent
Requires-Python: >=3.6
License-File: LICENSE
Requires-Dist: sqlparse (>=0.4.2)
Requires-Dist: sql-metadata (>=2.4.0)
Requires-Dist: rich (>=12.0.0)
Provides-Extra: testing
Requires-Dist: pytest (>=7.0) ; extra == 'testing'
Requires-Dist: pytest-cov (>=3.0) ; extra == 'testing'
Requires-Dist: mypy (>=0.910) ; extra == 'testing'
Requires-Dist: types-setuptools (>=57.4.10) ; extra == 'testing'
Requires-Dist: flake8 (>=4.0) ; extra == 'testing'
Requires-Dist: tox (>=3.24) ; extra == 'testing'
